epymorph/__init__.py
epymorph/__main__.py
epymorph/attribute.py
epymorph/cache.py
epymorph/compartment_model.py
epymorph/data_shape.py
epymorph/data_type.py
epymorph/data_usage.py
epymorph/database.py
epymorph/error.py
epymorph/event.py
epymorph/initializer.py
epymorph/kit.py
epymorph/movement_model.py
epymorph/params.py
epymorph/py.typed
epymorph/rume.py
epymorph/settings.py
epymorph/simulation.py
epymorph/strata.py
epymorph/sympy_shim.py
epymorph/time.py
epymorph/util.py
epymorph/adrio/__init__.py
epymorph/adrio/acs5.py
epymorph/adrio/adrio.py
epymorph/adrio/cdc.py
epymorph/adrio/commuting_flows.py
epymorph/adrio/csv.py
epymorph/adrio/humidity.py
epymorph/adrio/lodes.py
epymorph/adrio/numpy.py
epymorph/adrio/prism.py
epymorph/adrio/processing.py
epymorph/adrio/soda.py
epymorph/adrio/us_tiger.py
epymorph/adrio/validation.py
epymorph/cli/__init__.py
epymorph/cli/cache.py
epymorph/cli/main.py
epymorph/data/__init__.py
epymorph/data/pei.py
epymorph/data/ipm/__init__.py
epymorph/data/ipm/no.py
epymorph/data/ipm/pei.py
epymorph/data/ipm/seirs.py
epymorph/data/ipm/sirh.py
epymorph/data/ipm/sirs.py
epymorph/data/ipm/sparsemod.py
epymorph/data/mm/__init__.py
epymorph/data/mm/centroids.py
epymorph/data/mm/flat.py
epymorph/data/mm/icecube.py
epymorph/data/mm/no.py
epymorph/data/mm/pei.py
epymorph/data/mm/sparsemod.py
epymorph/geography/__init__.py
epymorph/geography/custom.py
epymorph/geography/scope.py
epymorph/geography/us_census.py
epymorph/geography/us_geography.py
epymorph/geography/us_tiger.py
epymorph/log/__init__.py
epymorph/log/file.py
epymorph/log/messaging.py
epymorph/log/movement.py
epymorph/parameter_fitting/__init__.py
epymorph/parameter_fitting/distribution.py
epymorph/parameter_fitting/dynamics.py
epymorph/parameter_fitting/likelihood.py
epymorph/parameter_fitting/output.py
epymorph/parameter_fitting/particlefilter_simulation.py
epymorph/parameter_fitting/perturbation.py
epymorph/parameter_fitting/filter/__init__.py
epymorph-1.1.0.dist-info/METADATA
epymorph-1.1.0.dist-info/WHEEL
epymorph-1.1.0.dist-info/entry_points.txt
epymorph-1.1.0.dist-info/top_level.txt
epymorph-1.1.0.dist-info/RECORD
