Metadata-Version: 2.4
Name: epymorph
Version: 1.1.0
Summary: EpiMoRPH spatial disease modeling
Author-email: Tyler Coles <tyler.coles@nau.edu>, Jeffrey Covington <jeffrey.covington@nau.edu>, Ye Chen <ye.chen@nau.edu>, Eck Doerry <eck.doerry@nau.edu>, Joseph Mihaljevic <joseph.mihaljevic@nau.edu>
License: GPL-3.0-only
Project-URL: Homepage, https://docs.www.epimorph.org
Project-URL: Source, https://github.com/NAU-CCL/Epymorph
Project-URL: Issues, https://github.com/NAU-CCL/Epymorph/issues
Keywords: epidemiology,disease modeling,metapopulation
Classifier: Programming Language :: Python :: 3
Classifier: Programming Language :: Python :: 3.11
Classifier: Programming Language :: Python :: 3.12
Classifier: Programming Language :: Python :: 3.13
Classifier: Operating System :: OS Independent
Classifier: Intended Audience :: Science/Research
Classifier: Topic :: Scientific/Engineering :: Bio-Informatics
Classifier: License :: OSI Approved :: GNU General Public License v3 (GPLv3)
Classifier: Typing :: Typed
Classifier: Development Status :: 5 - Production/Stable
Requires-Python: >=3.11
Requires-Dist: matplotlib~=3.9.0
Requires-Dist: numpy~=1.26.4
Requires-Dist: sympy~=1.12.1
Requires-Dist: psutil~=5.9.8
Requires-Dist: pandas[excel]~=2.2.2
Requires-Dist: geopandas~=0.14.4
Requires-Dist: census~=0.8.22
Requires-Dist: jsonpickle~=3.2.1
Requires-Dist: platformdirs~=4.2.2
Requires-Dist: graphviz~=0.20.3
Requires-Dist: typing_extensions~=4.12.2
Requires-Dist: ipython~=8.26.0
Requires-Dist: rasterio~=1.3.11
Requires-Dist: humanize~=4.10.0
Requires-Dist: sparklines~=0.5.0
Requires-Dist: scipy~=1.14.1
